ExecutorService/__main__.py
ExecutorService/const.py
ExecutorService/service.py
sgb_executor-0.2.dist-info/METADATA
sgb_executor-0.2.dist-info/WHEEL
sgb_executor-0.2.dist-info/entry_points.txt
sgb_executor-0.2.dist-info/top_level.txt
sgb_executor-0.2.dist-info/RECORD
